text2graph/__init__.py
text2graph/concept_extractor.py
text2graph/graph_builder.py
open_ttg-0.0.0.4.dist-info/LICENSE
open_ttg-0.0.0.4.dist-info/METADATA
open_ttg-0.0.0.4.dist-info/WHEEL
open_ttg-0.0.0.4.dist-info/top_level.txt
open_ttg-0.0.0.4.dist-info/RECORD
