Metadata-Version: 2.1
Name: open-ttg
Version: 0.0.0.4
Summary: graph builder from text
Home-page: https://github.com/monkitect/text2graph.git
Author: monkitect.com
Author-email: 1304646911@qq.com
License: UNKNOWN
Project-URL: Bug Tracker, https://github.com/monkitect/text2graph/issues
Platform: UNKNOWN
Classifier: Programming Language :: Python :: 3
Classifier: License :: OSI Approved :: MIT License
Classifier: Operating System :: OS Independent
Requires-Python: >=3.6
License-File: LICENSE
Requires-Dist: jieba
